{
    "features": [
        {
            "geometry": {
                "coordinates": [
                    5.4266,
                    43.3909
                ],
                "type": "Point"
            },
            "properties": {
                "is_installed": true,
                "is_renting": true,
                "is_returning": true,
                "last_reported": 1702765302,
                "name": "Marseille",
                "num_bikes_available": 1769,
                "num_docks_available": 999999,
                "station_id": "marseille"
            },
            "type": "Feature"
        }
    ],
    "type": "FeatureCollection"
}